CPILake_Utils/CPILake_Utils.py
CPILake_Utils/__init__.py
cpilake_utils-21.0.0.dist-info/METADATA
cpilake_utils-21.0.0.dist-info/WHEEL
cpilake_utils-21.0.0.dist-info/top_level.txt
cpilake_utils-21.0.0.dist-info/RECORD
