Metadata-Version: 2.4
Name: CPILake_Utils
Version: 21.0.0
Summary: Reusable common utility functions including email and hash functions
Author: Abhilash Ibrahimpatnam
Requires-Python: >=3.8
Requires-Dist: requests
